discopula/__init__.py
discopula/checkerboard/__init__.py
discopula/checkerboard/gencopula.py
discopula/checkerboard/genstatsim.py
discopula/checkerboard/utils.py
docs/__init__.py
docs/conf.py
tests/__init__.py
tests/test_gencopula.py
tests/test_genstatsim.py
tests/test_utils.py
discopula-0.5.2.dist-info/LICENSE.txt
discopula-0.5.2.dist-info/METADATA
discopula-0.5.2.dist-info/WHEEL
discopula-0.5.2.dist-info/top_level.txt
discopula-0.5.2.dist-info/RECORD
