Metadata-Version: 2.2
Name: discopula
Version: 0.5.2
Summary: This package is for discrete copula modeling and implementation of new scoring methods pertaining to ordinal and categorical discrete data.
Home-page: https://github.com/dmavani25/discopula
Author: Dhyey Mavani
License: MIT
Keywords: discrete-copula
Classifier: Programming Language :: Cython
Classifier: Programming Language :: Python
Classifier: Programming Language :: Python :: 3
Classifier: License :: OSI Approved :: MIT License
Classifier: Operating System :: OS Independent
Requires-Python: >=3.8
License-File: LICENSE.txt
Requires-Dist: numpy
Requires-Dist: scipy
Requires-Dist: matplotlib
Dynamic: author
Dynamic: classifier
Dynamic: description
Dynamic: description-content-type
Dynamic: home-page
Dynamic: keywords
Dynamic: license
Dynamic: requires-dist
Dynamic: requires-python
Dynamic: summary
